<?xml version="1.0"?>
<!DOCTYPE hibernate-mapping PUBLIC "-//Hibernate/Hibernate Mapping DTD 3.0//EN" "http://www.hibernate.org/dtd/hibernate-mapping-3.0.dtd">

<hibernate-mapping auto-import="false" default-lazy="false">
	<import class="com.nbp.osi.insolvency.application.form.services.model.AssessmentIndividualPersonalDetails" />
	<import class="com.nbp.osi.insolvency.application.form.services.model.AssetsNotUsedAsSecurity" />
	<import class="com.nbp.osi.insolvency.application.form.services.model.AssetsUsedAsSecurity" />
	<import class="com.nbp.osi.insolvency.application.form.services.model.CompanyDetails" />
	<import class="com.nbp.osi.insolvency.application.form.services.model.CompanyFinancialPosition" />
	<import class="com.nbp.osi.insolvency.application.form.services.model.CompanySecretary" />
	<import class="com.nbp.osi.insolvency.application.form.services.model.CompanySecuredCreditor" />
	<import class="com.nbp.osi.insolvency.application.form.services.model.CompanyTotalLiability" />
	<import class="com.nbp.osi.insolvency.application.form.services.model.CompanyUnsecuredCreditor" />
	<import class="com.nbp.osi.insolvency.application.form.services.model.DirectorsForm" />
	<import class="com.nbp.osi.insolvency.application.form.services.model.FinancialPosition" />
	<import class="com.nbp.osi.insolvency.application.form.services.model.GrandTotal" />
	<import class="com.nbp.osi.insolvency.application.form.services.model.MonthlyExpenses" />
	<import class="com.nbp.osi.insolvency.application.form.services.model.MonthlyIncome" />
	<import class="com.nbp.osi.insolvency.application.form.services.model.NotUsedSecurity" />
	<import class="com.nbp.osi.insolvency.application.form.services.model.OsiAssesmentDetailsOfAsset" />
	<import class="com.nbp.osi.insolvency.application.form.services.model.OsiAssessmentSignature" />
	<import class="com.nbp.osi.insolvency.application.form.services.model.OsiComSecurityTotal" />
	<import class="com.nbp.osi.insolvency.application.form.services.model.OsiComTotalLiability" />
	<import class="com.nbp.osi.insolvency.application.form.services.model.OsiIndiTotalDetailOfAssets" />
	<import class="com.nbp.osi.insolvency.application.form.services.model.OsiInsolvencyApplication" />
	<import class="com.nbp.osi.insolvency.application.form.services.model.OsiInsolvencyApplicationPayment" />
	<import class="com.nbp.osi.insolvency.application.form.services.model.OsiInsolvencyCurrentStage" />
	<import class="com.nbp.osi.insolvency.application.form.services.model.OsiInsolvPaymentPlan" />
	<import class="com.nbp.osi.insolvency.application.form.services.model.OsiTotalMonthlyExpense" />
	<import class="com.nbp.osi.insolvency.application.form.services.model.PreferredCreditor" />
	<import class="com.nbp.osi.insolvency.application.form.services.model.SecuredCreditor" />
	<import class="com.nbp.osi.insolvency.application.form.services.model.ShareholdersHoldings" />
	<import class="com.nbp.osi.insolvency.application.form.services.model.SubjectData" />
	<import class="com.nbp.osi.insolvency.application.form.services.model.UnsecuredCreditor" />
	<import class="com.nbp.osi.insolvency.application.form.services.model.UsedSecurity" />
	<import class="com.nbp.osi.insolvency.application.form.services.model.VerificationCompanyInfo" />
	<import class="com.nbp.osi.insolvency.application.form.services.model.VerificationRequestorsInfo" />
	<class name="com.nbp.osi.insolvency.application.form.services.model.impl.AssessmentIndividualPersonalDetailsImpl" table="nbp_osi_assessment_detail">
		<id access="com.liferay.portal.dao.orm.hibernate.MethodPropertyAccessor" name="assessmentDetailsId" type="long">
			<generator class="assigned" />
		</id>
		<property access="com.liferay.portal.dao.orm.hibernate.MethodPropertyAccessor" name="groupId" type="com.liferay.portal.dao.orm.hibernate.LongType" />
		<property access="com.liferay.portal.dao.orm.hibernate.MethodPropertyAccessor" name="initialDateContact" type="org.hibernate.type.TimestampType" />
		<property access="com.liferay.portal.dao.orm.hibernate.MethodPropertyAccessor" name="personalName" type="com.liferay.portal.dao.orm.hibernate.StringType" />
		<property access="com.liferay.portal.dao.orm.hibernate.MethodPropertyAccessor" name="personalAddress" type="com.liferay.portal.dao.orm.hibernate.StringType" />
		<property access="com.liferay.portal.dao.orm.hibernate.MethodPropertyAccessor" name="personalEmail" type="com.liferay.portal.dao.orm.hibernate.StringType" />
		<property access="com.liferay.portal.dao.orm.hibernate.MethodPropertyAccessor" name="personalTelNum" type="com.liferay.portal.dao.orm.hibernate.StringType" />
		<property access="com.liferay.portal.dao.orm.hibernate.MethodPropertyAccessor" name="personalTrn" type="com.liferay.portal.dao.orm.hibernate.StringType" />
		<property access="com.liferay.portal.dao.orm.hibernate.MethodPropertyAccessor" name="personalNis" type="com.liferay.portal.dao.orm.hibernate.StringType" />
		<property access="com.liferay.portal.dao.orm.hibernate.MethodPropertyAccessor" name="personalDob" type="org.hibernate.type.TimestampType" />
		<property access="com.liferay.portal.dao.orm.hibernate.MethodPropertyAccessor" name="personalAge" type="com.liferay.portal.dao.orm.hibernate.StringType" />
		<property access="com.liferay.portal.dao.orm.hibernate.MethodPropertyAccessor" name="personalMaritalStatus" type="com.liferay.portal.dao.orm.hibernate.StringType" />
		<property access="com.liferay.portal.dao.orm.hibernate.MethodPropertyAccessor" name="personalDependents" type="com.liferay.portal.dao.orm.hibernate.StringType" />
		<property access="com.liferay.portal.dao.orm.hibernate.MethodPropertyAccessor" name="personalOccupation" type="com.liferay.portal.dao.orm.hibernate.StringType" />
		<property access="com.liferay.portal.dao.orm.hibernate.MethodPropertyAccessor" name="emergencyName" type="com.liferay.portal.dao.orm.hibernate.StringType" />
		<property access="com.liferay.portal.dao.orm.hibernate.MethodPropertyAccessor" name="emergencyEmail" type="com.liferay.portal.dao.orm.hibernate.StringType" />
		<property access="com.liferay.portal.dao.orm.hibernate.MethodPropertyAccessor" name="emergencyTelNum" type="com.liferay.portal.dao.orm.hibernate.StringType" />
		<property access="com.liferay.portal.dao.orm.hibernate.MethodPropertyAccessor" name="emergencyAddress" type="com.liferay.portal.dao.orm.hibernate.StringType" />
		<property access="com.liferay.portal.dao.orm.hibernate.MethodPropertyAccessor" name="emergencyEmployer" type="com.liferay.portal.dao.orm.hibernate.StringType" />
		<property access="com.liferay.portal.dao.orm.hibernate.MethodPropertyAccessor" name="employerAddress" type="com.liferay.portal.dao.orm.hibernate.StringType" />
		<property access="com.liferay.portal.dao.orm.hibernate.MethodPropertyAccessor" name="employerEmail" type="com.liferay.portal.dao.orm.hibernate.StringType" />
		<property access="com.liferay.portal.dao.orm.hibernate.MethodPropertyAccessor" name="employerTelNum" type="com.liferay.portal.dao.orm.hibernate.StringType" />
		<property access="com.liferay.portal.dao.orm.hibernate.MethodPropertyAccessor" name="osiInsolvencyId" type="com.liferay.portal.dao.orm.hibernate.LongType" />
	</class>
	<class name="com.nbp.osi.insolvency.application.form.services.model.impl.AssetsNotUsedAsSecurityImpl" table="nbp_osi_not_used_security">
		<id access="com.liferay.portal.dao.orm.hibernate.MethodPropertyAccessor" name="assetsNotUsedAsSecurityId" type="long">
			<generator class="assigned" />
		</id>
		<property access="com.liferay.portal.dao.orm.hibernate.MethodPropertyAccessor" name="groupId" type="com.liferay.portal.dao.orm.hibernate.LongType" />
		<property access="com.liferay.portal.dao.orm.hibernate.MethodPropertyAccessor" name="companyId" type="com.liferay.portal.dao.orm.hibernate.LongType" />
		<property access="com.liferay.portal.dao.orm.hibernate.MethodPropertyAccessor" name="userId" type="com.liferay.portal.dao.orm.hibernate.LongType" />
		<property access="com.liferay.portal.dao.orm.hibernate.MethodPropertyAccessor" name="userName" type="com.liferay.portal.dao.orm.hibernate.StringType" />
		<property access="com.liferay.portal.dao.orm.hibernate.MethodPropertyAccessor" name="createDate" type="org.hibernate.type.TimestampType" />
		<property access="com.liferay.portal.dao.orm.hibernate.MethodPropertyAccessor" name="modifiedDate" type="org.hibernate.type.TimestampType" />
		<property access="com.liferay.portal.dao.orm.hibernate.MethodPropertyAccessor" name="assetRealProp" type="com.liferay.portal.dao.orm.hibernate.StringType" />
		<property access="com.liferay.portal.dao.orm.hibernate.MethodPropertyAccessor" name="assetNoValue" type="com.liferay.portal.dao.orm.hibernate.StringType" />
		<property access="com.liferay.portal.dao.orm.hibernate.MethodPropertyAccessor" name="assetDescription" type="com.liferay.portal.dao.orm.hibernate.StringType" />
		<property access="com.liferay.portal.dao.orm.hibernate.MethodPropertyAccessor" name="assetNoCounter" type="com.liferay.portal.dao.orm.hibernate.StringType" />
		<property access="com.liferay.portal.dao.orm.hibernate.MethodPropertyAccessor" name="comTotalAssetNotUsedSecurity" type="com.liferay.portal.dao.orm.hibernate.StringType" />
		<property access="com.liferay.portal.dao.orm.hibernate.MethodPropertyAccessor" name="osiInsolvencyId" type="com.liferay.portal.dao.orm.hibernate.LongType" />
	</class>
	<class name="com.nbp.osi.insolvency.application.form.services.model.impl.AssetsUsedAsSecurityImpl" table="nbp_osi_used_as_security">
		<id access="com.liferay.portal.dao.orm.hibernate.MethodPropertyAccessor" name="assetsUsedAsSecurityId" type="long">
			<generator class="assigned" />
		</id>
		<property access="com.liferay.portal.dao.orm.hibernate.MethodPropertyAccessor" name="groupId" type="com.liferay.portal.dao.orm.hibernate.LongType" />
		<property access="com.liferay.portal.dao.orm.hibernate.MethodPropertyAccessor" name="companyId" type="com.liferay.portal.dao.orm.hibernate.LongType" />
		<property access="com.liferay.portal.dao.orm.hibernate.MethodPropertyAccessor" name="userId" type="com.liferay.portal.dao.orm.hibernate.LongType" />
		<property access="com.liferay.portal.dao.orm.hibernate.MethodPropertyAccessor" name="userName" type="com.liferay.portal.dao.orm.hibernate.StringType" />
		<property access="com.liferay.portal.dao.orm.hibernate.MethodPropertyAccessor" name="createDate" type="org.hibernate.type.TimestampType" />
		<property access="com.liferay.portal.dao.orm.hibernate.MethodPropertyAccessor" name="modifiedDate" type="org.hibernate.type.TimestampType" />
		<property access="com.liferay.portal.dao.orm.hibernate.MethodPropertyAccessor" name="assetSecurity" type="com.liferay.portal.dao.orm.hibernate.StringType" />
		<property access="com.liferay.portal.dao.orm.hibernate.MethodPropertyAccessor" name="assetSecurityHolder" type="com.liferay.portal.dao.orm.hibernate.StringType" />
		<property access="com.liferay.portal.dao.orm.hibernate.MethodPropertyAccessor" name="assetDetails" type="com.liferay.portal.dao.orm.hibernate.StringType" />
		<property access="com.liferay.portal.dao.orm.hibernate.MethodPropertyAccessor" name="assetValue" type="com.liferay.portal.dao.orm.hibernate.StringType" />
		<property access="com.liferay.portal.dao.orm.hibernate.MethodPropertyAccessor" name="assetLiability" type="com.liferay.portal.dao.orm.hibernate.StringType" />
		<property access="com.liferay.portal.dao.orm.hibernate.MethodPropertyAccessor" name="assetNetValue" type="com.liferay.portal.dao.orm.hibernate.StringType" />
		<property access="com.liferay.portal.dao.orm.hibernate.MethodPropertyAccessor" name="assetCounter" type="com.liferay.portal.dao.orm.hibernate.StringType" />
		<property access="com.liferay.portal.dao.orm.hibernate.MethodPropertyAccessor" name="comTotalAssetUsedSecurity" type="com.liferay.portal.dao.orm.hibernate.StringType" />
		<property access="com.liferay.portal.dao.orm.hibernate.MethodPropertyAccessor" name="osiInsolvencyId" type="com.liferay.portal.dao.orm.hibernate.LongType" />
	</class>
	<class name="com.nbp.osi.insolvency.application.form.services.model.impl.CompanyDetailsImpl" table="nbp_osi_company_details">
		<id access="com.liferay.portal.dao.orm.hibernate.MethodPropertyAccessor" name="companyDetailsId" type="long">
			<generator class="assigned" />
		</id>
		<property access="com.liferay.portal.dao.orm.hibernate.MethodPropertyAccessor" name="groupId" type="com.liferay.portal.dao.orm.hibernate.LongType" />
		<property access="com.liferay.portal.dao.orm.hibernate.MethodPropertyAccessor" name="companyId" type="com.liferay.portal.dao.orm.hibernate.LongType" />
		<property access="com.liferay.portal.dao.orm.hibernate.MethodPropertyAccessor" name="userId" type="com.liferay.portal.dao.orm.hibernate.LongType" />
		<property access="com.liferay.portal.dao.orm.hibernate.MethodPropertyAccessor" name="userName" type="com.liferay.portal.dao.orm.hibernate.StringType" />
		<property access="com.liferay.portal.dao.orm.hibernate.MethodPropertyAccessor" name="createDate" type="org.hibernate.type.TimestampType" />
		<property access="com.liferay.portal.dao.orm.hibernate.MethodPropertyAccessor" name="modifiedDate" type="org.hibernate.type.TimestampType" />
		<property access="com.liferay.portal.dao.orm.hibernate.MethodPropertyAccessor" name="companyDate" type="org.hibernate.type.TimestampType" />
		<property access="com.liferay.portal.dao.orm.hibernate.MethodPropertyAccessor" name="companyName" type="com.liferay.portal.dao.orm.hibernate.StringType" />
		<property access="com.liferay.portal.dao.orm.hibernate.MethodPropertyAccessor" name="companyAddress" type="com.liferay.portal.dao.orm.hibernate.StringType" />
		<property access="com.liferay.portal.dao.orm.hibernate.MethodPropertyAccessor" name="companyEmail" type="com.liferay.portal.dao.orm.hibernate.StringType" />
		<property access="com.liferay.portal.dao.orm.hibernate.MethodPropertyAccessor" name="companyTelNum" type="com.liferay.portal.dao.orm.hibernate.StringType" />
		<property access="com.liferay.portal.dao.orm.hibernate.MethodPropertyAccessor" name="companyTrn" type="com.liferay.portal.dao.orm.hibernate.StringType" />
		<property access="com.liferay.portal.dao.orm.hibernate.MethodPropertyAccessor" name="companyDateInco" type="org.hibernate.type.TimestampType" />
		<property access="com.liferay.portal.dao.orm.hibernate.MethodPropertyAccessor" name="companyTypeOfCo" type="com.liferay.portal.dao.orm.hibernate.StringType" />
		<property access="com.liferay.portal.dao.orm.hibernate.MethodPropertyAccessor" name="companyCore" type="com.liferay.portal.dao.orm.hibernate.StringType" />
		<property access="com.liferay.portal.dao.orm.hibernate.MethodPropertyAccessor" name="companyEmployees" type="com.liferay.portal.dao.orm.hibernate.StringType" />
		<property access="com.liferay.portal.dao.orm.hibernate.MethodPropertyAccessor" name="companyLastReturn" type="org.hibernate.type.TimestampType" />
		<property access="com.liferay.portal.dao.orm.hibernate.MethodPropertyAccessor" name="companyTurnover" type="com.liferay.portal.dao.orm.hibernate.StringType" />
		<property access="com.liferay.portal.dao.orm.hibernate.MethodPropertyAccessor" name="companyShares" type="com.liferay.portal.dao.orm.hibernate.StringType" />
		<property access="com.liferay.portal.dao.orm.hibernate.MethodPropertyAccessor" name="osiInsolvencyId" type="com.liferay.portal.dao.orm.hibernate.LongType" />
	</class>
	<class name="com.nbp.osi.insolvency.application.form.services.model.impl.CompanyFinancialPositionImpl" table="nbp_osi_comp_financial_pos">
		<id access="com.liferay.portal.dao.orm.hibernate.MethodPropertyAccessor" name="companyFinancialPositionId" type="long">
			<generator class="assigned" />
		</id>
		<property access="com.liferay.portal.dao.orm.hibernate.MethodPropertyAccessor" name="groupId" type="com.liferay.portal.dao.orm.hibernate.LongType" />
		<property access="com.liferay.portal.dao.orm.hibernate.MethodPropertyAccessor" name="companyId" type="com.liferay.portal.dao.orm.hibernate.LongType" />
		<property access="com.liferay.portal.dao.orm.hibernate.MethodPropertyAccessor" name="userId" type="com.liferay.portal.dao.orm.hibernate.LongType" />
		<property access="com.liferay.portal.dao.orm.hibernate.MethodPropertyAccessor" name="userName" type="com.liferay.portal.dao.orm.hibernate.StringType" />
		<property access="com.liferay.portal.dao.orm.hibernate.MethodPropertyAccessor" name="createDate" type="org.hibernate.type.TimestampType" />
		<property access="com.liferay.portal.dao.orm.hibernate.MethodPropertyAccessor" name="modifiedDate" type="org.hibernate.type.TimestampType" />
		<property access="com.liferay.portal.dao.orm.hibernate.MethodPropertyAccessor" name="companySecured" type="com.liferay.portal.dao.orm.hibernate.StringType" />
		<property access="com.liferay.portal.dao.orm.hibernate.MethodPropertyAccessor" name="companyUnsecured" type="com.liferay.portal.dao.orm.hibernate.StringType" />
		<property access="com.liferay.portal.dao.orm.hibernate.MethodPropertyAccessor" name="companyAmount" type="com.liferay.portal.dao.orm.hibernate.StringType" />
		<property access="com.liferay.portal.dao.orm.hibernate.MethodPropertyAccessor" name="companyDeficit" type="com.liferay.portal.dao.orm.hibernate.StringType" />
		<property access="com.liferay.portal.dao.orm.hibernate.MethodPropertyAccessor" name="companyNetValue" type="com.liferay.portal.dao.orm.hibernate.StringType" />
		<property access="com.liferay.portal.dao.orm.hibernate.MethodPropertyAccessor" name="companyAssetValue" type="com.liferay.portal.dao.orm.hibernate.StringType" />
		<property access="com.liferay.portal.dao.orm.hibernate.MethodPropertyAccessor" name="companyDisposableAsset" type="com.liferay.portal.dao.orm.hibernate.StringType" />
		<property access="com.liferay.portal.dao.orm.hibernate.MethodPropertyAccessor" name="companySurplus" type="com.liferay.portal.dao.orm.hibernate.StringType" />
		<property access="com.liferay.portal.dao.orm.hibernate.MethodPropertyAccessor" name="companySummary" type="com.liferay.portal.dao.orm.hibernate.StringType" />
		<property access="com.liferay.portal.dao.orm.hibernate.MethodPropertyAccessor" name="companyProposal" type="com.liferay.portal.dao.orm.hibernate.StringType" />
		<property access="com.liferay.portal.dao.orm.hibernate.MethodPropertyAccessor" name="companyTrusteeResponse" type="com.liferay.portal.dao.orm.hibernate.StringType" />
		<property access="com.liferay.portal.dao.orm.hibernate.MethodPropertyAccessor" name="osiInsolvencyId" type="com.liferay.portal.dao.orm.hibernate.LongType" />
	</class>
	<class name="com.nbp.osi.insolvency.application.form.services.model.impl.CompanySecretaryImpl" table="nbp_osi_company_secretary">
		<id access="com.liferay.portal.dao.orm.hibernate.MethodPropertyAccessor" name="companySecretaryId" type="long">
			<generator class="assigned" />
		</id>
		<property access="com.liferay.portal.dao.orm.hibernate.MethodPropertyAccessor" name="groupId" type="com.liferay.portal.dao.orm.hibernate.LongType" />
		<property access="com.liferay.portal.dao.orm.hibernate.MethodPropertyAccessor" name="companyId" type="com.liferay.portal.dao.orm.hibernate.LongType" />
		<property access="com.liferay.portal.dao.orm.hibernate.MethodPropertyAccessor" name="userId" type="com.liferay.portal.dao.orm.hibernate.LongType" />
		<property access="com.liferay.portal.dao.orm.hibernate.MethodPropertyAccessor" name="userName" type="com.liferay.portal.dao.orm.hibernate.StringType" />
		<property access="com.liferay.portal.dao.orm.hibernate.MethodPropertyAccessor" name="createDate" type="org.hibernate.type.TimestampType" />
		<property access="com.liferay.portal.dao.orm.hibernate.MethodPropertyAccessor" name="modifiedDate" type="org.hibernate.type.TimestampType" />
		<property access="com.liferay.portal.dao.orm.hibernate.MethodPropertyAccessor" name="secretaryName" type="com.liferay.portal.dao.orm.hibernate.StringType" />
		<property access="com.liferay.portal.dao.orm.hibernate.MethodPropertyAccessor" name="secretaryDate" type="org.hibernate.type.TimestampType" />
		<property access="com.liferay.portal.dao.orm.hibernate.MethodPropertyAccessor" name="secretaryOccupation" type="com.liferay.portal.dao.orm.hibernate.StringType" />
		<property access="com.liferay.portal.dao.orm.hibernate.MethodPropertyAccessor" name="secretaryContactNum" type="com.liferay.portal.dao.orm.hibernate.StringType" />
		<property access="com.liferay.portal.dao.orm.hibernate.MethodPropertyAccessor" name="secretaryAddress" type="com.liferay.portal.dao.orm.hibernate.StringType" />
		<property access="com.liferay.portal.dao.orm.hibernate.MethodPropertyAccessor" name="secretaryCounter" type="com.liferay.portal.dao.orm.hibernate.StringType" />
		<property access="com.liferay.portal.dao.orm.hibernate.MethodPropertyAccessor" name="osiInsolvencyId" type="com.liferay.portal.dao.orm.hibernate.LongType" />
	</class>
	<class name="com.nbp.osi.insolvency.application.form.services.model.impl.CompanySecuredCreditorImpl" table="nbp_osi_secured_creditor">
		<id access="com.liferay.portal.dao.orm.hibernate.MethodPropertyAccessor" name="companySecuredCreditorId" type="long">
			<generator class="assigned" />
		</id>
		<property access="com.liferay.portal.dao.orm.hibernate.MethodPropertyAccessor" name="groupId" type="com.liferay.portal.dao.orm.hibernate.LongType" />
		<property access="com.liferay.portal.dao.orm.hibernate.MethodPropertyAccessor" name="companyId" type="com.liferay.portal.dao.orm.hibernate.LongType" />
		<property access="com.liferay.portal.dao.orm.hibernate.MethodPropertyAccessor" name="userId" type="com.liferay.portal.dao.orm.hibernate.LongType" />
		<property access="com.liferay.portal.dao.orm.hibernate.MethodPropertyAccessor" name="userName" type="com.liferay.portal.dao.orm.hibernate.StringType" />
		<property access="com.liferay.portal.dao.orm.hibernate.MethodPropertyAccessor" name="createDate" type="org.hibernate.type.TimestampType" />
		<property access="com.liferay.portal.dao.orm.hibernate.MethodPropertyAccessor" name="modifiedDate" type="org.hibernate.type.TimestampType" />
		<property access="com.liferay.portal.dao.orm.hibernate.MethodPropertyAccessor" name="securedCreditor" type="com.liferay.portal.dao.orm.hibernate.StringType" />
		<property access="com.liferay.portal.dao.orm.hibernate.MethodPropertyAccessor" name="securedSecurity" type="com.liferay.portal.dao.orm.hibernate.StringType" />
		<property access="com.liferay.portal.dao.orm.hibernate.MethodPropertyAccessor" name="securedPurpose" type="com.liferay.portal.dao.orm.hibernate.StringType" />
		<property access="com.liferay.portal.dao.orm.hibernate.MethodPropertyAccessor" name="securedLiabilty" type="com.liferay.portal.dao.orm.hibernate.StringType" />
		<property access="com.liferay.portal.dao.orm.hibernate.MethodPropertyAccessor" name="comSecurityValue" type="com.liferay.portal.dao.orm.hibernate.StringType" />
		<property access="com.liferay.portal.dao.orm.hibernate.MethodPropertyAccessor" name="comSecurityCounter" type="com.liferay.portal.dao.orm.hibernate.StringType" />
		<property access="com.liferay.portal.dao.orm.hibernate.MethodPropertyAccessor" name="osiInsolvencyId" type="com.liferay.portal.dao.orm.hibernate.LongType" />
	</class>
	<class name="com.nbp.osi.insolvency.application.form.services.model.impl.CompanyTotalLiabilityImpl" table="nbp_osi_insolv_total_liab">
		<id access="com.liferay.portal.dao.orm.hibernate.MethodPropertyAccessor" name="companyTotalLiabilityId" type="long">
			<generator class="assigned" />
		</id>
		<property access="com.liferay.portal.dao.orm.hibernate.MethodPropertyAccessor" name="groupId" type="com.liferay.portal.dao.orm.hibernate.LongType" />
		<property access="com.liferay.portal.dao.orm.hibernate.MethodPropertyAccessor" name="companyId" type="com.liferay.portal.dao.orm.hibernate.LongType" />
		<property access="com.liferay.portal.dao.orm.hibernate.MethodPropertyAccessor" name="userId" type="com.liferay.portal.dao.orm.hibernate.LongType" />
		<property access="com.liferay.portal.dao.orm.hibernate.MethodPropertyAccessor" name="userName" type="com.liferay.portal.dao.orm.hibernate.StringType" />
		<property access="com.liferay.portal.dao.orm.hibernate.MethodPropertyAccessor" name="createDate" type="org.hibernate.type.TimestampType" />
		<property access="com.liferay.portal.dao.orm.hibernate.MethodPropertyAccessor" name="modifiedDate" type="org.hibernate.type.TimestampType" />
		<property access="com.liferay.portal.dao.orm.hibernate.MethodPropertyAccessor" name="comTotalLiability" type="com.liferay.portal.dao.orm.hibernate.StringType" />
		<property access="com.liferay.portal.dao.orm.hibernate.MethodPropertyAccessor" name="osiInsolvencyId" type="com.liferay.portal.dao.orm.hibernate.LongType" />
	</class>
	<class name="com.nbp.osi.insolvency.application.form.services.model.impl.CompanyUnsecuredCreditorImpl" table="nbp_osi_unsecured_cred">
		<id access="com.liferay.portal.dao.orm.hibernate.MethodPropertyAccessor" name="companyUnsecuredCreditorId" type="long">
			<generator class="assigned" />
		</id>
		<property access="com.liferay.portal.dao.orm.hibernate.MethodPropertyAccessor" name="groupId" type="com.liferay.portal.dao.orm.hibernate.LongType" />
		<property access="com.liferay.portal.dao.orm.hibernate.MethodPropertyAccessor" name="companyId" type="com.liferay.portal.dao.orm.hibernate.LongType" />
		<property access="com.liferay.portal.dao.orm.hibernate.MethodPropertyAccessor" name="userId" type="com.liferay.portal.dao.orm.hibernate.LongType" />
		<property access="com.liferay.portal.dao.orm.hibernate.MethodPropertyAccessor" name="userName" type="com.liferay.portal.dao.orm.hibernate.StringType" />
		<property access="com.liferay.portal.dao.orm.hibernate.MethodPropertyAccessor" name="createDate" type="org.hibernate.type.TimestampType" />
		<property access="com.liferay.portal.dao.orm.hibernate.MethodPropertyAccessor" name="modifiedDate" type="org.hibernate.type.TimestampType" />
		<property access="com.liferay.portal.dao.orm.hibernate.MethodPropertyAccessor" name="unsecuredCreditor" type="com.liferay.portal.dao.orm.hibernate.StringType" />
		<property access="com.liferay.portal.dao.orm.hibernate.MethodPropertyAccessor" name="unsecuredDebtor" type="com.liferay.portal.dao.orm.hibernate.StringType" />
		<property access="com.liferay.portal.dao.orm.hibernate.MethodPropertyAccessor" name="unsecuredPurpose" type="com.liferay.portal.dao.orm.hibernate.StringType" />
		<property access="com.liferay.portal.dao.orm.hibernate.MethodPropertyAccessor" name="unsecuredLiabilty" type="com.liferay.portal.dao.orm.hibernate.StringType" />
		<property access="com.liferay.portal.dao.orm.hibernate.MethodPropertyAccessor" name="unsecuredCounter" type="com.liferay.portal.dao.orm.hibernate.StringType" />
		<property access="com.liferay.portal.dao.orm.hibernate.MethodPropertyAccessor" name="osiInsolvencyId" type="com.liferay.portal.dao.orm.hibernate.LongType" />
	</class>
	<class name="com.nbp.osi.insolvency.application.form.services.model.impl.DirectorsFormImpl" table="nbp_osi_directors_form">
		<id access="com.liferay.portal.dao.orm.hibernate.MethodPropertyAccessor" name="directorsFormId" type="long">
			<generator class="assigned" />
		</id>
		<property access="com.liferay.portal.dao.orm.hibernate.MethodPropertyAccessor" name="groupId" type="com.liferay.portal.dao.orm.hibernate.LongType" />
		<property access="com.liferay.portal.dao.orm.hibernate.MethodPropertyAccessor" name="companyId" type="com.liferay.portal.dao.orm.hibernate.LongType" />
		<property access="com.liferay.portal.dao.orm.hibernate.MethodPropertyAccessor" name="userId" type="com.liferay.portal.dao.orm.hibernate.LongType" />
		<property access="com.liferay.portal.dao.orm.hibernate.MethodPropertyAccessor" name="userName" type="com.liferay.portal.dao.orm.hibernate.StringType" />
		<property access="com.liferay.portal.dao.orm.hibernate.MethodPropertyAccessor" name="createDate" type="org.hibernate.type.TimestampType" />
		<property access="com.liferay.portal.dao.orm.hibernate.MethodPropertyAccessor" name="modifiedDate" type="org.hibernate.type.TimestampType" />
		<property access="com.liferay.portal.dao.orm.hibernate.MethodPropertyAccessor" name="directorsName" type="com.liferay.portal.dao.orm.hibernate.StringType" />
		<property access="com.liferay.portal.dao.orm.hibernate.MethodPropertyAccessor" name="directorsDateAppointed" type="org.hibernate.type.TimestampType" />
		<property access="com.liferay.portal.dao.orm.hibernate.MethodPropertyAccessor" name="directorsOccupation" type="com.liferay.portal.dao.orm.hibernate.StringType" />
		<property access="com.liferay.portal.dao.orm.hibernate.MethodPropertyAccessor" name="directorsContactNum" type="com.liferay.portal.dao.orm.hibernate.StringType" />
		<property access="com.liferay.portal.dao.orm.hibernate.MethodPropertyAccessor" name="directorsAddress" type="com.liferay.portal.dao.orm.hibernate.StringType" />
		<property access="com.liferay.portal.dao.orm.hibernate.MethodPropertyAccessor" name="directorsCounter" type="com.liferay.portal.dao.orm.hibernate.StringType" />
		<property access="com.liferay.portal.dao.orm.hibernate.MethodPropertyAccessor" name="osiInsolvencyId" type="com.liferay.portal.dao.orm.hibernate.LongType" />
	</class>
	<class name="com.nbp.osi.insolvency.application.form.services.model.impl.FinancialPositionImpl" table="nbp_osi_financial_position">
		<id access="com.liferay.portal.dao.orm.hibernate.MethodPropertyAccessor" name="financialPositionId" type="long">
			<generator class="assigned" />
		</id>
		<property access="com.liferay.portal.dao.orm.hibernate.MethodPropertyAccessor" name="groupId" type="com.liferay.portal.dao.orm.hibernate.LongType" />
		<property access="com.liferay.portal.dao.orm.hibernate.MethodPropertyAccessor" name="companyId" type="com.liferay.portal.dao.orm.hibernate.LongType" />
		<property access="com.liferay.portal.dao.orm.hibernate.MethodPropertyAccessor" name="userId" type="com.liferay.portal.dao.orm.hibernate.LongType" />
		<property access="com.liferay.portal.dao.orm.hibernate.MethodPropertyAccessor" name="userName" type="com.liferay.portal.dao.orm.hibernate.StringType" />
		<property access="com.liferay.portal.dao.orm.hibernate.MethodPropertyAccessor" name="createDate" type="org.hibernate.type.TimestampType" />
		<property access="com.liferay.portal.dao.orm.hibernate.MethodPropertyAccessor" name="modifiedDate" type="org.hibernate.type.TimestampType" />
		<property access="com.liferay.portal.dao.orm.hibernate.MethodPropertyAccessor" name="securedLiabilities" type="com.liferay.portal.dao.orm.hibernate.StringType" />
		<property access="com.liferay.portal.dao.orm.hibernate.MethodPropertyAccessor" name="unsecuredLiabilities" type="com.liferay.portal.dao.orm.hibernate.StringType" />
		<property access="com.liferay.portal.dao.orm.hibernate.MethodPropertyAccessor" name="amountLiabilities" type="com.liferay.portal.dao.orm.hibernate.StringType" />
		<property access="com.liferay.portal.dao.orm.hibernate.MethodPropertyAccessor" name="deficitLiabilities" type="com.liferay.portal.dao.orm.hibernate.StringType" />
		<property access="com.liferay.portal.dao.orm.hibernate.MethodPropertyAccessor" name="assestsUsedAsSecurity" type="com.liferay.portal.dao.orm.hibernate.StringType" />
		<property access="com.liferay.portal.dao.orm.hibernate.MethodPropertyAccessor" name="assestsNotUsedAsSecurity" type="com.liferay.portal.dao.orm.hibernate.StringType" />
		<property access="com.liferay.portal.dao.orm.hibernate.MethodPropertyAccessor" name="assestsDisposable" type="com.liferay.portal.dao.orm.hibernate.StringType" />
		<property access="com.liferay.portal.dao.orm.hibernate.MethodPropertyAccessor" name="assestsSurplus" type="com.liferay.portal.dao.orm.hibernate.StringType" />
		<property access="com.liferay.portal.dao.orm.hibernate.MethodPropertyAccessor" name="assestsSummary" type="com.liferay.portal.dao.orm.hibernate.StringType" />
		<property access="com.liferay.portal.dao.orm.hibernate.MethodPropertyAccessor" name="assestsProposal" type="com.liferay.portal.dao.orm.hibernate.StringType" />
		<property access="com.liferay.portal.dao.orm.hibernate.MethodPropertyAccessor" name="assestsTrusteeResponse" type="com.liferay.portal.dao.orm.hibernate.StringType" />
		<property access="com.liferay.portal.dao.orm.hibernate.MethodPropertyAccessor" name="osiInsolvencyId" type="com.liferay.portal.dao.orm.hibernate.LongType" />
	</class>
	<class name="com.nbp.osi.insolvency.application.form.services.model.impl.GrandTotalImpl" table="nbp_osi_grand_total">
		<id access="com.liferay.portal.dao.orm.hibernate.MethodPropertyAccessor" name="grandTotalId" type="long">
			<generator class="assigned" />
		</id>
		<property access="com.liferay.portal.dao.orm.hibernate.MethodPropertyAccessor" name="groupId" type="com.liferay.portal.dao.orm.hibernate.LongType" />
		<property access="com.liferay.portal.dao.orm.hibernate.MethodPropertyAccessor" name="companyId" type="com.liferay.portal.dao.orm.hibernate.LongType" />
		<property access="com.liferay.portal.dao.orm.hibernate.MethodPropertyAccessor" name="userId" type="com.liferay.portal.dao.orm.hibernate.LongType" />
		<property access="com.liferay.portal.dao.orm.hibernate.MethodPropertyAccessor" name="userName" type="com.liferay.portal.dao.orm.hibernate.StringType" />
		<property access="com.liferay.portal.dao.orm.hibernate.MethodPropertyAccessor" name="createDate" type="org.hibernate.type.TimestampType" />
		<property access="com.liferay.portal.dao.orm.hibernate.MethodPropertyAccessor" name="modifiedDate" type="org.hibernate.type.TimestampType" />
		<property access="com.liferay.portal.dao.orm.hibernate.MethodPropertyAccessor" name="totalSecuredLiabilities" type="com.liferay.portal.dao.orm.hibernate.StringType" />
		<property access="com.liferay.portal.dao.orm.hibernate.MethodPropertyAccessor" name="securedTotalMonthlyPayments" type="com.liferay.portal.dao.orm.hibernate.StringType" />
		<property access="com.liferay.portal.dao.orm.hibernate.MethodPropertyAccessor" name="totalPreferredLiabilities" type="com.liferay.portal.dao.orm.hibernate.StringType" />
		<property access="com.liferay.portal.dao.orm.hibernate.MethodPropertyAccessor" name="preferredTotalMonthlyPayments" type="com.liferay.portal.dao.orm.hibernate.StringType" />
		<property access="com.liferay.portal.dao.orm.hibernate.MethodPropertyAccessor" name="totalUnsecuredLiabilities" type="com.liferay.portal.dao.orm.hibernate.StringType" />
		<property access="com.liferay.portal.dao.orm.hibernate.MethodPropertyAccessor" name="unsecuredTotalMonthlyPayments" type="com.liferay.portal.dao.orm.hibernate.StringType" />
		<property access="com.liferay.portal.dao.orm.hibernate.MethodPropertyAccessor" name="grandTotal" type="com.liferay.portal.dao.orm.hibernate.StringType" />
		<property access="com.liferay.portal.dao.orm.hibernate.MethodPropertyAccessor" name="osiInsolvencyId" type="com.liferay.portal.dao.orm.hibernate.LongType" />
	</class>
	<class name="com.nbp.osi.insolvency.application.form.services.model.impl.MonthlyExpensesImpl" table="nbp_osi_monthly_expense">
		<id access="com.liferay.portal.dao.orm.hibernate.MethodPropertyAccessor" name="monthlyExpensesId" type="long">
			<generator class="assigned" />
		</id>
		<property access="com.liferay.portal.dao.orm.hibernate.MethodPropertyAccessor" name="groupId" type="com.liferay.portal.dao.orm.hibernate.LongType" />
		<property access="com.liferay.portal.dao.orm.hibernate.MethodPropertyAccessor" name="companyId" type="com.liferay.portal.dao.orm.hibernate.LongType" />
		<property access="com.liferay.portal.dao.orm.hibernate.MethodPropertyAccessor" name="userId" type="com.liferay.portal.dao.orm.hibernate.LongType" />
		<property access="com.liferay.portal.dao.orm.hibernate.MethodPropertyAccessor" name="userName" type="com.liferay.portal.dao.orm.hibernate.StringType" />
		<property access="com.liferay.portal.dao.orm.hibernate.MethodPropertyAccessor" name="createDate" type="org.hibernate.type.TimestampType" />
		<property access="com.liferay.portal.dao.orm.hibernate.MethodPropertyAccessor" name="modifiedDate" type="org.hibernate.type.TimestampType" />
		<property access="com.liferay.portal.dao.orm.hibernate.MethodPropertyAccessor" name="typeOfExpense" type="com.liferay.portal.dao.orm.hibernate.StringType" />
		<property access="com.liferay.portal.dao.orm.hibernate.MethodPropertyAccessor" name="lightExpense" type="com.liferay.portal.dao.orm.hibernate.StringType" />
		<property access="com.liferay.portal.dao.orm.hibernate.MethodPropertyAccessor" name="cableExpense" type="com.liferay.portal.dao.orm.hibernate.StringType" />
		<property access="com.liferay.portal.dao.orm.hibernate.MethodPropertyAccessor" name="waterExpense" type="com.liferay.portal.dao.orm.hibernate.StringType" />
		<property access="com.liferay.portal.dao.orm.hibernate.MethodPropertyAccessor" name="expenseCounter" type="com.liferay.portal.dao.orm.hibernate.StringType" />
		<property access="com.liferay.portal.dao.orm.hibernate.MethodPropertyAccessor" name="telephoneExpense" type="com.liferay.portal.dao.orm.hibernate.StringType" />
		<property access="com.liferay.portal.dao.orm.hibernate.MethodPropertyAccessor" name="osiInsolvencyId" type="com.liferay.portal.dao.orm.hibernate.LongType" />
	</class>
	<class name="com.nbp.osi.insolvency.application.form.services.model.impl.MonthlyIncomeImpl" table="nbp_osi_monthly_income">
		<id access="com.liferay.portal.dao.orm.hibernate.MethodPropertyAccessor" name="monthlyIncomeId" type="long">
			<generator class="assigned" />
		</id>
		<property access="com.liferay.portal.dao.orm.hibernate.MethodPropertyAccessor" name="groupId" type="com.liferay.portal.dao.orm.hibernate.LongType" />
		<property access="com.liferay.portal.dao.orm.hibernate.MethodPropertyAccessor" name="companyId" type="com.liferay.portal.dao.orm.hibernate.LongType" />
		<property access="com.liferay.portal.dao.orm.hibernate.MethodPropertyAccessor" name="userId" type="com.liferay.portal.dao.orm.hibernate.LongType" />
		<property access="com.liferay.portal.dao.orm.hibernate.MethodPropertyAccessor" name="userName" type="com.liferay.portal.dao.orm.hibernate.StringType" />
		<property access="com.liferay.portal.dao.orm.hibernate.MethodPropertyAccessor" name="createDate" type="org.hibernate.type.TimestampType" />
		<property access="com.liferay.portal.dao.orm.hibernate.MethodPropertyAccessor" name="modifiedDate" type="org.hibernate.type.TimestampType" />
		<property access="com.liferay.portal.dao.orm.hibernate.MethodPropertyAccessor" name="basicSalary" type="com.liferay.portal.dao.orm.hibernate.StringType" />
		<property access="com.liferay.portal.dao.orm.hibernate.MethodPropertyAccessor" name="grossSalary" type="com.liferay.portal.dao.orm.hibernate.StringType" />
		<property access="com.liferay.portal.dao.orm.hibernate.MethodPropertyAccessor" name="statutoryDeduction" type="com.liferay.portal.dao.orm.hibernate.StringType" />
		<property access="com.liferay.portal.dao.orm.hibernate.MethodPropertyAccessor" name="otherDeductions" type="com.liferay.portal.dao.orm.hibernate.StringType" />
		<property access="com.liferay.portal.dao.orm.hibernate.MethodPropertyAccessor" name="loanDeductions" type="com.liferay.portal.dao.orm.hibernate.StringType" />
		<property access="com.liferay.portal.dao.orm.hibernate.MethodPropertyAccessor" name="totalDeductions" type="com.liferay.portal.dao.orm.hibernate.StringType" />
		<property access="com.liferay.portal.dao.orm.hibernate.MethodPropertyAccessor" name="netSalary" type="com.liferay.portal.dao.orm.hibernate.StringType" />
		<property access="com.liferay.portal.dao.orm.hibernate.MethodPropertyAccessor" name="otherIncome" type="com.liferay.portal.dao.orm.hibernate.StringType" />
		<property access="com.liferay.portal.dao.orm.hibernate.MethodPropertyAccessor" name="incomeToCover" type="com.liferay.portal.dao.orm.hibernate.StringType" />
		<property access="com.liferay.portal.dao.orm.hibernate.MethodPropertyAccessor" name="osiInsolvencyId" type="com.liferay.portal.dao.orm.hibernate.LongType" />
	</class>
	<class name="com.nbp.osi.insolvency.application.form.services.model.impl.NotUsedSecurityImpl" table="nbp_not_used_security">
		<id access="com.liferay.portal.dao.orm.hibernate.MethodPropertyAccessor" name="notUsedSecurityId" type="long">
			<generator class="assigned" />
		</id>
		<property access="com.liferay.portal.dao.orm.hibernate.MethodPropertyAccessor" name="groupId" type="com.liferay.portal.dao.orm.hibernate.LongType" />
		<property access="com.liferay.portal.dao.orm.hibernate.MethodPropertyAccessor" name="companyId" type="com.liferay.portal.dao.orm.hibernate.LongType" />
		<property access="com.liferay.portal.dao.orm.hibernate.MethodPropertyAccessor" name="userId" type="com.liferay.portal.dao.orm.hibernate.LongType" />
		<property access="com.liferay.portal.dao.orm.hibernate.MethodPropertyAccessor" name="userName" type="com.liferay.portal.dao.orm.hibernate.StringType" />
		<property access="com.liferay.portal.dao.orm.hibernate.MethodPropertyAccessor" name="createDate" type="org.hibernate.type.TimestampType" />
		<property access="com.liferay.portal.dao.orm.hibernate.MethodPropertyAccessor" name="modifiedDate" type="org.hibernate.type.TimestampType" />
		<property access="com.liferay.portal.dao.orm.hibernate.MethodPropertyAccessor" name="realProperty" type="com.liferay.portal.dao.orm.hibernate.StringType" />
		<property access="com.liferay.portal.dao.orm.hibernate.MethodPropertyAccessor" name="notUsedLocation" type="com.liferay.portal.dao.orm.hibernate.StringType" />
		<property access="com.liferay.portal.dao.orm.hibernate.MethodPropertyAccessor" name="notUsedDescription" type="com.liferay.portal.dao.orm.hibernate.StringType" />
		<property access="com.liferay.portal.dao.orm.hibernate.MethodPropertyAccessor" name="notUsedCounter" type="com.liferay.portal.dao.orm.hibernate.StringType" />
		<property access="com.liferay.portal.dao.orm.hibernate.MethodPropertyAccessor" name="notUsedValue" type="com.liferay.portal.dao.orm.hibernate.StringType" />
		<property access="com.liferay.portal.dao.orm.hibernate.MethodPropertyAccessor" name="notNetValue" type="com.liferay.portal.dao.orm.hibernate.StringType" />
		<property access="com.liferay.portal.dao.orm.hibernate.MethodPropertyAccessor" name="osiInsolvencyId" type="com.liferay.portal.dao.orm.hibernate.LongType" />
	</class>
	<class name="com.nbp.osi.insolvency.application.form.services.model.impl.OsiAssesmentDetailsOfAssetImpl" table="nbp_osi_insolvecy_det_asset">
		<id access="com.liferay.portal.dao.orm.hibernate.MethodPropertyAccessor" name="osiAssetDetailsId" type="long">
			<generator class="assigned" />
		</id>
		<property access="com.liferay.portal.dao.orm.hibernate.MethodPropertyAccessor" name="groupId" type="com.liferay.portal.dao.orm.hibernate.LongType" />
		<property access="com.liferay.portal.dao.orm.hibernate.MethodPropertyAccessor" name="companyId" type="com.liferay.portal.dao.orm.hibernate.LongType" />
		<property access="com.liferay.portal.dao.orm.hibernate.MethodPropertyAccessor" name="userId" type="com.liferay.portal.dao.orm.hibernate.LongType" />
		<property access="com.liferay.portal.dao.orm.hibernate.MethodPropertyAccessor" name="userName" type="com.liferay.portal.dao.orm.hibernate.StringType" />
		<property access="com.liferay.portal.dao.orm.hibernate.MethodPropertyAccessor" name="createDate" type="org.hibernate.type.TimestampType" />
		<property access="com.liferay.portal.dao.orm.hibernate.MethodPropertyAccessor" name="modifiedDate" type="org.hibernate.type.TimestampType" />
		<property access="com.liferay.portal.dao.orm.hibernate.MethodPropertyAccessor" name="totalAssetUsedAsSecurity" type="com.liferay.portal.dao.orm.hibernate.StringType" />
		<property access="com.liferay.portal.dao.orm.hibernate.MethodPropertyAccessor" name="totalAssetNotUsedAsSec" type="com.liferay.portal.dao.orm.hibernate.StringType" />
		<property access="com.liferay.portal.dao.orm.hibernate.MethodPropertyAccessor" name="totalValuesOfAsset" type="com.liferay.portal.dao.orm.hibernate.StringType" />
		<property access="com.liferay.portal.dao.orm.hibernate.MethodPropertyAccessor" name="osiInsolvencyId" type="com.liferay.portal.dao.orm.hibernate.LongType" />
	</class>
	<class name="com.nbp.osi.insolvency.application.form.services.model.impl.OsiAssessmentSignatureImpl" table="nbp_osi_insolvecy_asses_sign">
		<id access="com.liferay.portal.dao.orm.hibernate.MethodPropertyAccessor" name="osiAssessmentSignatureId" type="long">
			<generator class="assigned" />
		</id>
		<property access="com.liferay.portal.dao.orm.hibernate.MethodPropertyAccessor" name="groupId" type="com.liferay.portal.dao.orm.hibernate.LongType" />
		<property access="com.liferay.portal.dao.orm.hibernate.MethodPropertyAccessor" name="companyId" type="com.liferay.portal.dao.orm.hibernate.LongType" />
		<property access="com.liferay.portal.dao.orm.hibernate.MethodPropertyAccessor" name="userId" type="com.liferay.portal.dao.orm.hibernate.LongType" />
		<property access="com.liferay.portal.dao.orm.hibernate.MethodPropertyAccessor" name="userName" type="com.liferay.portal.dao.orm.hibernate.StringType" />
		<property access="com.liferay.portal.dao.orm.hibernate.MethodPropertyAccessor" name="createDate" type="org.hibernate.type.TimestampType" />
		<property access="com.liferay.portal.dao.orm.hibernate.MethodPropertyAccessor" name="modifiedDate" type="org.hibernate.type.TimestampType" />
		<property access="com.liferay.portal.dao.orm.hibernate.MethodPropertyAccessor" name="assessSignName" type="com.liferay.portal.dao.orm.hibernate.StringType" />
		<property access="com.liferay.portal.dao.orm.hibernate.MethodPropertyAccessor" name="assessSignDate" type="com.liferay.portal.dao.orm.hibernate.StringType" />
		<property access="com.liferay.portal.dao.orm.hibernate.MethodPropertyAccessor" name="osiInsolvencyId" type="com.liferay.portal.dao.orm.hibernate.LongType" />
	</class>
	<class name="com.nbp.osi.insolvency.application.form.services.model.impl.OsiComSecurityTotalImpl" table="nbp_insolv_com_security_tot">
		<id access="com.liferay.portal.dao.orm.hibernate.MethodPropertyAccessor" name="osiComSecurityTotalId" type="long">
			<generator class="assigned" />
		</id>
		<property access="com.liferay.portal.dao.orm.hibernate.MethodPropertyAccessor" name="groupId" type="com.liferay.portal.dao.orm.hibernate.LongType" />
		<property access="com.liferay.portal.dao.orm.hibernate.MethodPropertyAccessor" name="companyId" type="com.liferay.portal.dao.orm.hibernate.LongType" />
		<property access="com.liferay.portal.dao.orm.hibernate.MethodPropertyAccessor" name="userId" type="com.liferay.portal.dao.orm.hibernate.LongType" />
		<property access="com.liferay.portal.dao.orm.hibernate.MethodPropertyAccessor" name="userName" type="com.liferay.portal.dao.orm.hibernate.StringType" />
		<property access="com.liferay.portal.dao.orm.hibernate.MethodPropertyAccessor" name="createDate" type="org.hibernate.type.TimestampType" />
		<property access="com.liferay.portal.dao.orm.hibernate.MethodPropertyAccessor" name="modifiedDate" type="org.hibernate.type.TimestampType" />
		<property access="com.liferay.portal.dao.orm.hibernate.MethodPropertyAccessor" name="comSecuritTotal" type="com.liferay.portal.dao.orm.hibernate.StringType" />
		<property access="com.liferay.portal.dao.orm.hibernate.MethodPropertyAccessor" name="comAssetTotal" type="com.liferay.portal.dao.orm.hibernate.StringType" />
		<property access="com.liferay.portal.dao.orm.hibernate.MethodPropertyAccessor" name="comSecuritTotalValue" type="com.liferay.portal.dao.orm.hibernate.StringType" />
		<property access="com.liferay.portal.dao.orm.hibernate.MethodPropertyAccessor" name="osiInsolvencyId" type="com.liferay.portal.dao.orm.hibernate.LongType" />
	</class>
	<class name="com.nbp.osi.insolvency.application.form.services.model.impl.OsiComTotalLiabilityImpl" table="nbp_osi_insolv_tot_liablity">
		<id access="com.liferay.portal.dao.orm.hibernate.MethodPropertyAccessor" name="osiComTotalLiabilityId" type="long">
			<generator class="assigned" />
		</id>
		<property access="com.liferay.portal.dao.orm.hibernate.MethodPropertyAccessor" name="groupId" type="com.liferay.portal.dao.orm.hibernate.LongType" />
		<property access="com.liferay.portal.dao.orm.hibernate.MethodPropertyAccessor" name="companyId" type="com.liferay.portal.dao.orm.hibernate.LongType" />
		<property access="com.liferay.portal.dao.orm.hibernate.MethodPropertyAccessor" name="userId" type="com.liferay.portal.dao.orm.hibernate.LongType" />
		<property access="com.liferay.portal.dao.orm.hibernate.MethodPropertyAccessor" name="userName" type="com.liferay.portal.dao.orm.hibernate.StringType" />
		<property access="com.liferay.portal.dao.orm.hibernate.MethodPropertyAccessor" name="createDate" type="org.hibernate.type.TimestampType" />
		<property access="com.liferay.portal.dao.orm.hibernate.MethodPropertyAccessor" name="modifiedDate" type="org.hibernate.type.TimestampType" />
		<property access="com.liferay.portal.dao.orm.hibernate.MethodPropertyAccessor" name="totalLiability" type="com.liferay.portal.dao.orm.hibernate.StringType" />
		<property access="com.liferay.portal.dao.orm.hibernate.MethodPropertyAccessor" name="osiInsolvencyId" type="com.liferay.portal.dao.orm.hibernate.LongType" />
	</class>
	<class name="com.nbp.osi.insolvency.application.form.services.model.impl.OsiIndiTotalDetailOfAssetsImpl" table="nbp_osi_insolv_tot_assets">
		<id access="com.liferay.portal.dao.orm.hibernate.MethodPropertyAccessor" name="osiIndiTotalDetailOfAssetsId" type="long">
			<generator class="assigned" />
		</id>
		<property access="com.liferay.portal.dao.orm.hibernate.MethodPropertyAccessor" name="groupId" type="com.liferay.portal.dao.orm.hibernate.LongType" />
		<property access="com.liferay.portal.dao.orm.hibernate.MethodPropertyAccessor" name="companyId" type="com.liferay.portal.dao.orm.hibernate.LongType" />
		<property access="com.liferay.portal.dao.orm.hibernate.MethodPropertyAccessor" name="userId" type="com.liferay.portal.dao.orm.hibernate.LongType" />
		<property access="com.liferay.portal.dao.orm.hibernate.MethodPropertyAccessor" name="userName" type="com.liferay.portal.dao.orm.hibernate.StringType" />
		<property access="com.liferay.portal.dao.orm.hibernate.MethodPropertyAccessor" name="createDate" type="org.hibernate.type.TimestampType" />
		<property access="com.liferay.portal.dao.orm.hibernate.MethodPropertyAccessor" name="modifiedDate" type="org.hibernate.type.TimestampType" />
		<property access="com.liferay.portal.dao.orm.hibernate.MethodPropertyAccessor" name="totalValueOfAssetUsedSecu" type="com.liferay.portal.dao.orm.hibernate.StringType" />
		<property access="com.liferay.portal.dao.orm.hibernate.MethodPropertyAccessor" name="totalValueOfAssetNotUsedSecu" type="com.liferay.portal.dao.orm.hibernate.StringType" />
		<property access="com.liferay.portal.dao.orm.hibernate.MethodPropertyAccessor" name="osiInsolvencyId" type="com.liferay.portal.dao.orm.hibernate.LongType" />
	</class>
	<class name="com.nbp.osi.insolvency.application.form.services.model.impl.OsiInsolvencyApplicationImpl" table="nbp_osi_insolv_application">
		<id access="com.liferay.portal.dao.orm.hibernate.MethodPropertyAccessor" name="osiInsolvencyId" type="long">
			<generator class="assigned" />
		</id>
		<property access="com.liferay.portal.dao.orm.hibernate.MethodPropertyAccessor" name="groupId" type="com.liferay.portal.dao.orm.hibernate.LongType" />
		<property access="com.liferay.portal.dao.orm.hibernate.MethodPropertyAccessor" name="companyId" type="com.liferay.portal.dao.orm.hibernate.LongType" />
		<property access="com.liferay.portal.dao.orm.hibernate.MethodPropertyAccessor" name="userId" type="com.liferay.portal.dao.orm.hibernate.LongType" />
		<property access="com.liferay.portal.dao.orm.hibernate.MethodPropertyAccessor" name="userName" type="com.liferay.portal.dao.orm.hibernate.StringType" />
		<property access="com.liferay.portal.dao.orm.hibernate.MethodPropertyAccessor" name="createDate" type="org.hibernate.type.TimestampType" />
		<property access="com.liferay.portal.dao.orm.hibernate.MethodPropertyAccessor" name="modifiedDate" type="org.hibernate.type.TimestampType" />
		<property access="com.liferay.portal.dao.orm.hibernate.MethodPropertyAccessor" name="entityId" type="com.liferay.portal.dao.orm.hibernate.StringType" />
		<property access="com.liferay.portal.dao.orm.hibernate.MethodPropertyAccessor" name="applicantStatus" type="com.liferay.portal.dao.orm.hibernate.StringType" />
		<property access="com.liferay.portal.dao.orm.hibernate.MethodPropertyAccessor" name="typeOfApplicant" type="com.liferay.portal.dao.orm.hibernate.StringType" />
		<property access="com.liferay.portal.dao.orm.hibernate.MethodPropertyAccessor" name="subjectData" type="com.liferay.portal.dao.orm.hibernate.StringType" />
		<property access="com.liferay.portal.dao.orm.hibernate.MethodPropertyAccessor" name="applicantIndividual" type="com.liferay.portal.dao.orm.hibernate.StringType" />
		<property access="com.liferay.portal.dao.orm.hibernate.MethodPropertyAccessor" name="applicantCompany" type="com.liferay.portal.dao.orm.hibernate.StringType" />
		<property access="com.liferay.portal.dao.orm.hibernate.MethodPropertyAccessor" name="realEstateBoard" type="com.liferay.portal.dao.orm.hibernate.StringType" />
		<property access="com.liferay.portal.dao.orm.hibernate.MethodPropertyAccessor" name="caseId" type="com.liferay.portal.dao.orm.hibernate.StringType" />
		<property access="com.liferay.portal.dao.orm.hibernate.MethodPropertyAccessor" name="status" type="com.liferay.portal.dao.orm.hibernate.IntegerType" />
		<property access="com.liferay.portal.dao.orm.hibernate.MethodPropertyAccessor" name="icmDocumentPath" type="com.liferay.portal.dao.orm.hibernate.StringType" />
		<property access="com.liferay.portal.dao.orm.hibernate.MethodPropertyAccessor" name="applicationNumber" type="com.liferay.portal.dao.orm.hibernate.StringType" />
		<property access="com.liferay.portal.dao.orm.hibernate.MethodPropertyAccessor" name="pdfFileEntryId" type="com.liferay.portal.dao.orm.hibernate.LongType" />
		<property access="com.liferay.portal.dao.orm.hibernate.MethodPropertyAccessor" name="appCurrentStageName" type="com.liferay.portal.dao.orm.hibernate.StringType" />
	</class>
	<class name="com.nbp.osi.insolvency.application.form.services.model.impl.OsiInsolvencyApplicationPaymentImpl" table="nbp_osi_insolvecy_app_payment">
		<id access="com.liferay.portal.dao.orm.hibernate.MethodPropertyAccessor" name="osiInsolveApplicationPaymentId" type="long">
			<generator class="assigned" />
		</id>
		<property access="com.liferay.portal.dao.orm.hibernate.MethodPropertyAccessor" name="groupId" type="com.liferay.portal.dao.orm.hibernate.LongType" />
		<property access="com.liferay.portal.dao.orm.hibernate.MethodPropertyAccessor" name="companyId" type="com.liferay.portal.dao.orm.hibernate.LongType" />
		<property access="com.liferay.portal.dao.orm.hibernate.MethodPropertyAccessor" name="userId" type="com.liferay.portal.dao.orm.hibernate.LongType" />
		<property access="com.liferay.portal.dao.orm.hibernate.MethodPropertyAccessor" name="userName" type="com.liferay.portal.dao.orm.hibernate.StringType" />
		<property access="com.liferay.portal.dao.orm.hibernate.MethodPropertyAccessor" name="createDate" type="org.hibernate.type.TimestampType" />
		<property access="com.liferay.portal.dao.orm.hibernate.MethodPropertyAccessor" name="modifiedDate" type="org.hibernate.type.TimestampType" />
		<property access="com.liferay.portal.dao.orm.hibernate.MethodPropertyAccessor" name="paymentMethod" type="com.liferay.portal.dao.orm.hibernate.StringType" />
		<property access="com.liferay.portal.dao.orm.hibernate.MethodPropertyAccessor" name="paymentDocId" type="com.liferay.portal.dao.orm.hibernate.StringType" />
		<property access="com.liferay.portal.dao.orm.hibernate.MethodPropertyAccessor" name="paymentStatus" type="com.liferay.portal.dao.orm.hibernate.StringType" />
		<property access="com.liferay.portal.dao.orm.hibernate.MethodPropertyAccessor" name="paymentFee" type="com.liferay.portal.dao.orm.hibernate.StringType" />
		<property access="com.liferay.portal.dao.orm.hibernate.MethodPropertyAccessor" name="amountPaid" type="com.liferay.portal.dao.orm.hibernate.StringType" />
		<property access="com.liferay.portal.dao.orm.hibernate.MethodPropertyAccessor" name="amountCurrency" type="com.liferay.portal.dao.orm.hibernate.StringType" />
		<property access="com.liferay.portal.dao.orm.hibernate.MethodPropertyAccessor" name="transactionNumber" type="com.liferay.portal.dao.orm.hibernate.StringType" />
		<property access="com.liferay.portal.dao.orm.hibernate.MethodPropertyAccessor" name="osiInsolvencyId" type="com.liferay.portal.dao.orm.hibernate.LongType" />
	</class>
	<class name="com.nbp.osi.insolvency.application.form.services.model.impl.OsiInsolvencyCurrentStageImpl" table="nbp_osi_insolv_current_stage">
		<id access="com.liferay.portal.dao.orm.hibernate.MethodPropertyAccessor" name="osiInsolvencyCurrentStageId" type="long">
			<generator class="assigned" />
		</id>
		<property access="com.liferay.portal.dao.orm.hibernate.MethodPropertyAccessor" name="osiInsolvencyStageId" type="com.liferay.portal.dao.orm.hibernate.LongType" />
		<property access="com.liferay.portal.dao.orm.hibernate.MethodPropertyAccessor" name="companyId" type="com.liferay.portal.dao.orm.hibernate.LongType" />
		<property access="com.liferay.portal.dao.orm.hibernate.MethodPropertyAccessor" name="userId" type="com.liferay.portal.dao.orm.hibernate.LongType" />
		<property access="com.liferay.portal.dao.orm.hibernate.MethodPropertyAccessor" name="userName" type="com.liferay.portal.dao.orm.hibernate.StringType" />
		<property access="com.liferay.portal.dao.orm.hibernate.MethodPropertyAccessor" name="createDate" type="org.hibernate.type.TimestampType" />
		<property access="com.liferay.portal.dao.orm.hibernate.MethodPropertyAccessor" name="modifiedDate" type="org.hibernate.type.TimestampType" />
		<property access="com.liferay.portal.dao.orm.hibernate.MethodPropertyAccessor" name="currentStage" type="com.liferay.portal.dao.orm.hibernate.StringType" />
		<property access="com.liferay.portal.dao.orm.hibernate.MethodPropertyAccessor" name="lastFormStage" type="com.liferay.portal.dao.orm.hibernate.StringType" />
		<property access="com.liferay.portal.dao.orm.hibernate.MethodPropertyAccessor" name="osiInsolvencyId" type="com.liferay.portal.dao.orm.hibernate.LongType" />
	</class>
	<class name="com.nbp.osi.insolvency.application.form.services.model.impl.OsiInsolvPaymentPlanImpl" table="nbp_osi_insolv_payment">
		<id access="com.liferay.portal.dao.orm.hibernate.MethodPropertyAccessor" name="osiInsolvPaymentPlanId" type="long">
			<generator class="assigned" />
		</id>
		<property access="com.liferay.portal.dao.orm.hibernate.MethodPropertyAccessor" name="groupId" type="com.liferay.portal.dao.orm.hibernate.LongType" />
		<property access="com.liferay.portal.dao.orm.hibernate.MethodPropertyAccessor" name="companyId" type="com.liferay.portal.dao.orm.hibernate.LongType" />
		<property access="com.liferay.portal.dao.orm.hibernate.MethodPropertyAccessor" name="userId" type="com.liferay.portal.dao.orm.hibernate.LongType" />
		<property access="com.liferay.portal.dao.orm.hibernate.MethodPropertyAccessor" name="userName" type="com.liferay.portal.dao.orm.hibernate.StringType" />
		<property access="com.liferay.portal.dao.orm.hibernate.MethodPropertyAccessor" name="createDate" type="org.hibernate.type.TimestampType" />
		<property access="com.liferay.portal.dao.orm.hibernate.MethodPropertyAccessor" name="modifiedDate" type="org.hibernate.type.TimestampType" />
		<property access="com.liferay.portal.dao.orm.hibernate.MethodPropertyAccessor" name="paymentMethod" type="com.liferay.portal.dao.orm.hibernate.StringType" />
		<property access="com.liferay.portal.dao.orm.hibernate.MethodPropertyAccessor" name="amountPaid" type="com.liferay.portal.dao.orm.hibernate.StringType" />
		<property access="com.liferay.portal.dao.orm.hibernate.MethodPropertyAccessor" name="paymentCurrencySelected" type="com.liferay.portal.dao.orm.hibernate.StringType" />
		<property access="com.liferay.portal.dao.orm.hibernate.MethodPropertyAccessor" name="paymentMethodOther" type="com.liferay.portal.dao.orm.hibernate.StringType" />
		<property access="com.liferay.portal.dao.orm.hibernate.MethodPropertyAccessor" name="paymentDocId" type="com.liferay.portal.dao.orm.hibernate.StringType" />
		<property access="com.liferay.portal.dao.orm.hibernate.MethodPropertyAccessor" name="osiInsolvencyId" type="com.liferay.portal.dao.orm.hibernate.LongType" />
	</class>
	<class name="com.nbp.osi.insolvency.application.form.services.model.impl.OsiTotalMonthlyExpenseImpl" table="nbp_osi_insolv_tot_expense">
		<id access="com.liferay.portal.dao.orm.hibernate.MethodPropertyAccessor" name="osiTotalMonthlyExpenseId" type="long">
			<generator class="assigned" />
		</id>
		<property access="com.liferay.portal.dao.orm.hibernate.MethodPropertyAccessor" name="groupId" type="com.liferay.portal.dao.orm.hibernate.LongType" />
		<property access="com.liferay.portal.dao.orm.hibernate.MethodPropertyAccessor" name="companyId" type="com.liferay.portal.dao.orm.hibernate.LongType" />
		<property access="com.liferay.portal.dao.orm.hibernate.MethodPropertyAccessor" name="userId" type="com.liferay.portal.dao.orm.hibernate.LongType" />
		<property access="com.liferay.portal.dao.orm.hibernate.MethodPropertyAccessor" name="userName" type="com.liferay.portal.dao.orm.hibernate.StringType" />
		<property access="com.liferay.portal.dao.orm.hibernate.MethodPropertyAccessor" name="createDate" type="org.hibernate.type.TimestampType" />
		<property access="com.liferay.portal.dao.orm.hibernate.MethodPropertyAccessor" name="modifiedDate" type="org.hibernate.type.TimestampType" />
		<property access="com.liferay.portal.dao.orm.hibernate.MethodPropertyAccessor" name="totalExpense" type="com.liferay.portal.dao.orm.hibernate.StringType" />
		<property access="com.liferay.portal.dao.orm.hibernate.MethodPropertyAccessor" name="osiInsolvencyId" type="com.liferay.portal.dao.orm.hibernate.LongType" />
	</class>
	<class name="com.nbp.osi.insolvency.application.form.services.model.impl.PreferredCreditorImpl" table="nbp_osi_preferred_detail">
		<id access="com.liferay.portal.dao.orm.hibernate.MethodPropertyAccessor" name="preferredCreditorId" type="long">
			<generator class="assigned" />
		</id>
		<property access="com.liferay.portal.dao.orm.hibernate.MethodPropertyAccessor" name="groupId" type="com.liferay.portal.dao.orm.hibernate.LongType" />
		<property access="com.liferay.portal.dao.orm.hibernate.MethodPropertyAccessor" name="companyId" type="com.liferay.portal.dao.orm.hibernate.LongType" />
		<property access="com.liferay.portal.dao.orm.hibernate.MethodPropertyAccessor" name="userId" type="com.liferay.portal.dao.orm.hibernate.LongType" />
		<property access="com.liferay.portal.dao.orm.hibernate.MethodPropertyAccessor" name="userName" type="com.liferay.portal.dao.orm.hibernate.StringType" />
		<property access="com.liferay.portal.dao.orm.hibernate.MethodPropertyAccessor" name="createDate" type="org.hibernate.type.TimestampType" />
		<property access="com.liferay.portal.dao.orm.hibernate.MethodPropertyAccessor" name="modifiedDate" type="org.hibernate.type.TimestampType" />
		<property access="com.liferay.portal.dao.orm.hibernate.MethodPropertyAccessor" name="preferredCreditorName" type="com.liferay.portal.dao.orm.hibernate.StringType" />
		<property access="com.liferay.portal.dao.orm.hibernate.MethodPropertyAccessor" name="preferredCreditorLiability" type="com.liferay.portal.dao.orm.hibernate.StringType" />
		<property access="com.liferay.portal.dao.orm.hibernate.MethodPropertyAccessor" name="preferredCreditorAmount" type="com.liferay.portal.dao.orm.hibernate.StringType" />
		<property access="com.liferay.portal.dao.orm.hibernate.MethodPropertyAccessor" name="preferredCreditorPayment" type="com.liferay.portal.dao.orm.hibernate.StringType" />
		<property access="com.liferay.portal.dao.orm.hibernate.MethodPropertyAccessor" name="preferredCreditorCounter" type="com.liferay.portal.dao.orm.hibernate.StringType" />
		<property access="com.liferay.portal.dao.orm.hibernate.MethodPropertyAccessor" name="preferredCreditorDate" type="org.hibernate.type.TimestampType" />
		<property access="com.liferay.portal.dao.orm.hibernate.MethodPropertyAccessor" name="osiInsolvencyId" type="com.liferay.portal.dao.orm.hibernate.LongType" />
	</class>
	<class name="com.nbp.osi.insolvency.application.form.services.model.impl.SecuredCreditorImpl" table="nbp_osi_liability_detail">
		<id access="com.liferay.portal.dao.orm.hibernate.MethodPropertyAccessor" name="securedCreditorId" type="long">
			<generator class="assigned" />
		</id>
		<property access="com.liferay.portal.dao.orm.hibernate.MethodPropertyAccessor" name="groupId" type="com.liferay.portal.dao.orm.hibernate.LongType" />
		<property access="com.liferay.portal.dao.orm.hibernate.MethodPropertyAccessor" name="companyId" type="com.liferay.portal.dao.orm.hibernate.LongType" />
		<property access="com.liferay.portal.dao.orm.hibernate.MethodPropertyAccessor" name="userId" type="com.liferay.portal.dao.orm.hibernate.LongType" />
		<property access="com.liferay.portal.dao.orm.hibernate.MethodPropertyAccessor" name="userName" type="com.liferay.portal.dao.orm.hibernate.StringType" />
		<property access="com.liferay.portal.dao.orm.hibernate.MethodPropertyAccessor" name="createDate" type="org.hibernate.type.TimestampType" />
		<property access="com.liferay.portal.dao.orm.hibernate.MethodPropertyAccessor" name="modifiedDate" type="org.hibernate.type.TimestampType" />
		<property access="com.liferay.portal.dao.orm.hibernate.MethodPropertyAccessor" name="securedCreditorName" type="com.liferay.portal.dao.orm.hibernate.StringType" />
		<property access="com.liferay.portal.dao.orm.hibernate.MethodPropertyAccessor" name="securedCreditorAsset" type="com.liferay.portal.dao.orm.hibernate.StringType" />
		<property access="com.liferay.portal.dao.orm.hibernate.MethodPropertyAccessor" name="securedCreditorLiability" type="com.liferay.portal.dao.orm.hibernate.StringType" />
		<property access="com.liferay.portal.dao.orm.hibernate.MethodPropertyAccessor" name="securedCreditorPayment" type="com.liferay.portal.dao.orm.hibernate.StringType" />
		<property access="com.liferay.portal.dao.orm.hibernate.MethodPropertyAccessor" name="securedCreditorCounter" type="com.liferay.portal.dao.orm.hibernate.StringType" />
		<property access="com.liferay.portal.dao.orm.hibernate.MethodPropertyAccessor" name="securedCreditorDate" type="org.hibernate.type.TimestampType" />
		<property access="com.liferay.portal.dao.orm.hibernate.MethodPropertyAccessor" name="osiInsolvencyId" type="com.liferay.portal.dao.orm.hibernate.LongType" />
	</class>
	<class name="com.nbp.osi.insolvency.application.form.services.model.impl.ShareholdersHoldingsImpl" table="nbp_osi_shareholder">
		<id access="com.liferay.portal.dao.orm.hibernate.MethodPropertyAccessor" name="shareholdersHoldingsId" type="long">
			<generator class="assigned" />
		</id>
		<property access="com.liferay.portal.dao.orm.hibernate.MethodPropertyAccessor" name="groupId" type="com.liferay.portal.dao.orm.hibernate.LongType" />
		<property access="com.liferay.portal.dao.orm.hibernate.MethodPropertyAccessor" name="companyId" type="com.liferay.portal.dao.orm.hibernate.LongType" />
		<property access="com.liferay.portal.dao.orm.hibernate.MethodPropertyAccessor" name="userId" type="com.liferay.portal.dao.orm.hibernate.LongType" />
		<property access="com.liferay.portal.dao.orm.hibernate.MethodPropertyAccessor" name="userName" type="com.liferay.portal.dao.orm.hibernate.StringType" />
		<property access="com.liferay.portal.dao.orm.hibernate.MethodPropertyAccessor" name="createDate" type="org.hibernate.type.TimestampType" />
		<property access="com.liferay.portal.dao.orm.hibernate.MethodPropertyAccessor" name="modifiedDate" type="org.hibernate.type.TimestampType" />
		<property access="com.liferay.portal.dao.orm.hibernate.MethodPropertyAccessor" name="shareholderName" type="com.liferay.portal.dao.orm.hibernate.StringType" />
		<property access="com.liferay.portal.dao.orm.hibernate.MethodPropertyAccessor" name="shareholderDate" type="org.hibernate.type.TimestampType" />
		<property access="com.liferay.portal.dao.orm.hibernate.MethodPropertyAccessor" name="shareholderOccupation" type="com.liferay.portal.dao.orm.hibernate.StringType" />
		<property access="com.liferay.portal.dao.orm.hibernate.MethodPropertyAccessor" name="shareholderShares" type="com.liferay.portal.dao.orm.hibernate.StringType" />
		<property access="com.liferay.portal.dao.orm.hibernate.MethodPropertyAccessor" name="shareholderAddress" type="com.liferay.portal.dao.orm.hibernate.StringType" />
		<property access="com.liferay.portal.dao.orm.hibernate.MethodPropertyAccessor" name="shareholderCounter" type="com.liferay.portal.dao.orm.hibernate.StringType" />
		<property access="com.liferay.portal.dao.orm.hibernate.MethodPropertyAccessor" name="osiInsolvencyId" type="com.liferay.portal.dao.orm.hibernate.LongType" />
	</class>
	<class name="com.nbp.osi.insolvency.application.form.services.model.impl.SubjectDataImpl" table="nbp_osi_subject_data">
		<id access="com.liferay.portal.dao.orm.hibernate.MethodPropertyAccessor" name="subjectDataId" type="long">
			<generator class="assigned" />
		</id>
		<property access="com.liferay.portal.dao.orm.hibernate.MethodPropertyAccessor" name="groupId" type="com.liferay.portal.dao.orm.hibernate.LongType" />
		<property access="com.liferay.portal.dao.orm.hibernate.MethodPropertyAccessor" name="companyId" type="com.liferay.portal.dao.orm.hibernate.LongType" />
		<property access="com.liferay.portal.dao.orm.hibernate.MethodPropertyAccessor" name="userId" type="com.liferay.portal.dao.orm.hibernate.LongType" />
		<property access="com.liferay.portal.dao.orm.hibernate.MethodPropertyAccessor" name="userName" type="com.liferay.portal.dao.orm.hibernate.StringType" />
		<property access="com.liferay.portal.dao.orm.hibernate.MethodPropertyAccessor" name="createDate" type="org.hibernate.type.TimestampType" />
		<property access="com.liferay.portal.dao.orm.hibernate.MethodPropertyAccessor" name="modifiedDate" type="org.hibernate.type.TimestampType" />
		<property access="com.liferay.portal.dao.orm.hibernate.MethodPropertyAccessor" name="verSubjectNameTitle" type="com.liferay.portal.dao.orm.hibernate.StringType" />
		<property access="com.liferay.portal.dao.orm.hibernate.MethodPropertyAccessor" name="verSubjectFirstName" type="com.liferay.portal.dao.orm.hibernate.StringType" />
		<property access="com.liferay.portal.dao.orm.hibernate.MethodPropertyAccessor" name="verSubjectMiddleName" type="com.liferay.portal.dao.orm.hibernate.StringType" />
		<property access="com.liferay.portal.dao.orm.hibernate.MethodPropertyAccessor" name="verSubjectSurname" type="com.liferay.portal.dao.orm.hibernate.StringType" />
		<property access="com.liferay.portal.dao.orm.hibernate.MethodPropertyAccessor" name="verSubjectDob" type="org.hibernate.type.TimestampType" />
		<property access="com.liferay.portal.dao.orm.hibernate.MethodPropertyAccessor" name="verPresentAddress" type="com.liferay.portal.dao.orm.hibernate.StringType" />
		<property access="com.liferay.portal.dao.orm.hibernate.MethodPropertyAccessor" name="verPlaceOfBirth" type="com.liferay.portal.dao.orm.hibernate.StringType" />
		<property access="com.liferay.portal.dao.orm.hibernate.MethodPropertyAccessor" name="verSubjectTrn" type="com.liferay.portal.dao.orm.hibernate.StringType" />
		<property access="com.liferay.portal.dao.orm.hibernate.MethodPropertyAccessor" name="verSubjectTelNum" type="com.liferay.portal.dao.orm.hibernate.StringType" />
		<property access="com.liferay.portal.dao.orm.hibernate.MethodPropertyAccessor" name="verSubjectEmail" type="com.liferay.portal.dao.orm.hibernate.StringType" />
		<property access="com.liferay.portal.dao.orm.hibernate.MethodPropertyAccessor" name="osiInsolvencyId" type="com.liferay.portal.dao.orm.hibernate.LongType" />
	</class>
	<class name="com.nbp.osi.insolvency.application.form.services.model.impl.UnsecuredCreditorImpl" table="nbp_osi_unsec_creditor">
		<id access="com.liferay.portal.dao.orm.hibernate.MethodPropertyAccessor" name="unsecuredCreditorId" type="long">
			<generator class="assigned" />
		</id>
		<property access="com.liferay.portal.dao.orm.hibernate.MethodPropertyAccessor" name="groupId" type="com.liferay.portal.dao.orm.hibernate.LongType" />
		<property access="com.liferay.portal.dao.orm.hibernate.MethodPropertyAccessor" name="companyId" type="com.liferay.portal.dao.orm.hibernate.LongType" />
		<property access="com.liferay.portal.dao.orm.hibernate.MethodPropertyAccessor" name="userId" type="com.liferay.portal.dao.orm.hibernate.LongType" />
		<property access="com.liferay.portal.dao.orm.hibernate.MethodPropertyAccessor" name="userName" type="com.liferay.portal.dao.orm.hibernate.StringType" />
		<property access="com.liferay.portal.dao.orm.hibernate.MethodPropertyAccessor" name="createDate" type="org.hibernate.type.TimestampType" />
		<property access="com.liferay.portal.dao.orm.hibernate.MethodPropertyAccessor" name="modifiedDate" type="org.hibernate.type.TimestampType" />
		<property access="com.liferay.portal.dao.orm.hibernate.MethodPropertyAccessor" name="unsecuredCreditorName" type="com.liferay.portal.dao.orm.hibernate.StringType" />
		<property access="com.liferay.portal.dao.orm.hibernate.MethodPropertyAccessor" name="unsecuredCreditorDebt" type="com.liferay.portal.dao.orm.hibernate.StringType" />
		<property access="com.liferay.portal.dao.orm.hibernate.MethodPropertyAccessor" name="unsecuredCreditorAmount" type="com.liferay.portal.dao.orm.hibernate.StringType" />
		<property access="com.liferay.portal.dao.orm.hibernate.MethodPropertyAccessor" name="unsecuredCreditorPayment" type="com.liferay.portal.dao.orm.hibernate.StringType" />
		<property access="com.liferay.portal.dao.orm.hibernate.MethodPropertyAccessor" name="unsecuredCreditorCounter" type="com.liferay.portal.dao.orm.hibernate.StringType" />
		<property access="com.liferay.portal.dao.orm.hibernate.MethodPropertyAccessor" name="unsecuredCreditorDate" type="org.hibernate.type.TimestampType" />
		<property access="com.liferay.portal.dao.orm.hibernate.MethodPropertyAccessor" name="osiInsolvencyId" type="com.liferay.portal.dao.orm.hibernate.LongType" />
	</class>
	<class name="com.nbp.osi.insolvency.application.form.services.model.impl.UsedSecurityImpl" table="nbp_osi_used_security">
		<id access="com.liferay.portal.dao.orm.hibernate.MethodPropertyAccessor" name="usedSecurityId" type="long">
			<generator class="assigned" />
		</id>
		<property access="com.liferay.portal.dao.orm.hibernate.MethodPropertyAccessor" name="groupId" type="com.liferay.portal.dao.orm.hibernate.LongType" />
		<property access="com.liferay.portal.dao.orm.hibernate.MethodPropertyAccessor" name="companyId" type="com.liferay.portal.dao.orm.hibernate.LongType" />
		<property access="com.liferay.portal.dao.orm.hibernate.MethodPropertyAccessor" name="userId" type="com.liferay.portal.dao.orm.hibernate.LongType" />
		<property access="com.liferay.portal.dao.orm.hibernate.MethodPropertyAccessor" name="userName" type="com.liferay.portal.dao.orm.hibernate.StringType" />
		<property access="com.liferay.portal.dao.orm.hibernate.MethodPropertyAccessor" name="createDate" type="org.hibernate.type.TimestampType" />
		<property access="com.liferay.portal.dao.orm.hibernate.MethodPropertyAccessor" name="modifiedDate" type="org.hibernate.type.TimestampType" />
		<property access="com.liferay.portal.dao.orm.hibernate.MethodPropertyAccessor" name="assetType" type="com.liferay.portal.dao.orm.hibernate.StringType" />
		<property access="com.liferay.portal.dao.orm.hibernate.MethodPropertyAccessor" name="securityHolder" type="com.liferay.portal.dao.orm.hibernate.StringType" />
		<property access="com.liferay.portal.dao.orm.hibernate.MethodPropertyAccessor" name="securityDetail" type="com.liferay.portal.dao.orm.hibernate.StringType" />
		<property access="com.liferay.portal.dao.orm.hibernate.MethodPropertyAccessor" name="securityValue" type="com.liferay.portal.dao.orm.hibernate.StringType" />
		<property access="com.liferay.portal.dao.orm.hibernate.MethodPropertyAccessor" name="securityLiability" type="com.liferay.portal.dao.orm.hibernate.StringType" />
		<property access="com.liferay.portal.dao.orm.hibernate.MethodPropertyAccessor" name="securityNetValue" type="com.liferay.portal.dao.orm.hibernate.StringType" />
		<property access="com.liferay.portal.dao.orm.hibernate.MethodPropertyAccessor" name="securityCounter" type="com.liferay.portal.dao.orm.hibernate.StringType" />
		<property access="com.liferay.portal.dao.orm.hibernate.MethodPropertyAccessor" name="osiInsolvencyId" type="com.liferay.portal.dao.orm.hibernate.LongType" />
	</class>
	<class name="com.nbp.osi.insolvency.application.form.services.model.impl.VerificationCompanyInfoImpl" table="nbp_osi_ver_company">
		<id access="com.liferay.portal.dao.orm.hibernate.MethodPropertyAccessor" name="verificationCompanyInfoId" type="long">
			<generator class="assigned" />
		</id>
		<property access="com.liferay.portal.dao.orm.hibernate.MethodPropertyAccessor" name="groupId" type="com.liferay.portal.dao.orm.hibernate.LongType" />
		<property access="com.liferay.portal.dao.orm.hibernate.MethodPropertyAccessor" name="companyId" type="com.liferay.portal.dao.orm.hibernate.LongType" />
		<property access="com.liferay.portal.dao.orm.hibernate.MethodPropertyAccessor" name="userId" type="com.liferay.portal.dao.orm.hibernate.LongType" />
		<property access="com.liferay.portal.dao.orm.hibernate.MethodPropertyAccessor" name="userName" type="com.liferay.portal.dao.orm.hibernate.StringType" />
		<property access="com.liferay.portal.dao.orm.hibernate.MethodPropertyAccessor" name="createDate" type="org.hibernate.type.TimestampType" />
		<property access="com.liferay.portal.dao.orm.hibernate.MethodPropertyAccessor" name="modifiedDate" type="org.hibernate.type.TimestampType" />
		<property access="com.liferay.portal.dao.orm.hibernate.MethodPropertyAccessor" name="verComName" type="com.liferay.portal.dao.orm.hibernate.StringType" />
		<property access="com.liferay.portal.dao.orm.hibernate.MethodPropertyAccessor" name="verComTrn" type="com.liferay.portal.dao.orm.hibernate.StringType" />
		<property access="com.liferay.portal.dao.orm.hibernate.MethodPropertyAccessor" name="osiInsolvencyId" type="com.liferay.portal.dao.orm.hibernate.LongType" />
	</class>
	<class name="com.nbp.osi.insolvency.application.form.services.model.impl.VerificationRequestorsInfoImpl" table="nbp_osi_ver_request_detail">
		<id access="com.liferay.portal.dao.orm.hibernate.MethodPropertyAccessor" name="requestorInformationId" type="long">
			<generator class="assigned" />
		</id>
		<property access="com.liferay.portal.dao.orm.hibernate.MethodPropertyAccessor" name="groupId" type="com.liferay.portal.dao.orm.hibernate.LongType" />
		<property access="com.liferay.portal.dao.orm.hibernate.MethodPropertyAccessor" name="companyId" type="com.liferay.portal.dao.orm.hibernate.LongType" />
		<property access="com.liferay.portal.dao.orm.hibernate.MethodPropertyAccessor" name="userId" type="com.liferay.portal.dao.orm.hibernate.LongType" />
		<property access="com.liferay.portal.dao.orm.hibernate.MethodPropertyAccessor" name="userName" type="com.liferay.portal.dao.orm.hibernate.StringType" />
		<property access="com.liferay.portal.dao.orm.hibernate.MethodPropertyAccessor" name="createDate" type="org.hibernate.type.TimestampType" />
		<property access="com.liferay.portal.dao.orm.hibernate.MethodPropertyAccessor" name="modifiedDate" type="org.hibernate.type.TimestampType" />
		<property access="com.liferay.portal.dao.orm.hibernate.MethodPropertyAccessor" name="verRequestorName" type="com.liferay.portal.dao.orm.hibernate.StringType" />
		<property access="com.liferay.portal.dao.orm.hibernate.MethodPropertyAccessor" name="verRequestorLastName" type="com.liferay.portal.dao.orm.hibernate.StringType" />
		<property access="com.liferay.portal.dao.orm.hibernate.MethodPropertyAccessor" name="verRequestorOccupation" type="com.liferay.portal.dao.orm.hibernate.StringType" />
		<property access="com.liferay.portal.dao.orm.hibernate.MethodPropertyAccessor" name="verRequestorAddress" type="com.liferay.portal.dao.orm.hibernate.StringType" />
		<property access="com.liferay.portal.dao.orm.hibernate.MethodPropertyAccessor" name="verDateOfRequest" type="org.hibernate.type.TimestampType" />
		<property access="com.liferay.portal.dao.orm.hibernate.MethodPropertyAccessor" name="verRequestorTelNum" type="com.liferay.portal.dao.orm.hibernate.StringType" />
		<property access="com.liferay.portal.dao.orm.hibernate.MethodPropertyAccessor" name="verRequestorEmail" type="com.liferay.portal.dao.orm.hibernate.StringType" />
		<property access="com.liferay.portal.dao.orm.hibernate.MethodPropertyAccessor" name="osiInsolvencyId" type="com.liferay.portal.dao.orm.hibernate.LongType" />
	</class>
</hibernate-mapping>